lichess/__init__.py
lichess/bot.py
lichess/client.py
lichess/endpoints.py
lichess/exceptions.py
lichess/models.py
lichess/utils.py
lithon-1.0.1.dist-info/LICENSE
lithon-1.0.1.dist-info/METADATA
lithon-1.0.1.dist-info/WHEEL
lithon-1.0.1.dist-info/top_level.txt
lithon-1.0.1.dist-info/RECORD
