Metadata-Version: 2.1
Name: lithon
Version: 1.0.1
Summary: A basic API wrapper for Lichess.
Home-page: https://github.com/Infiniticity/lithon
Author: Omkaar
Author-email: omkaar.nerurkar@gmail.com
License: MIT
Classifier: License :: OSI Approved :: MIT License
Classifier: Natural Language :: English
Classifier: Programming Language :: Python
Classifier: Programming Language :: Python :: 3
Requires-Python: >= 3.8.0
License-File: LICENSE
Requires-Dist: requests
